[
    {
        "title": "UE,GENTILONI: \"EVITATA LA RECESSIONE\"  Ma ancora in \"un periodo difficile\"",
        "date_raw": "February 14, 2023",
        "date": "2023-02-14",
        "url": "http://www.servizitelevideo.rai.it/televideo/pub/solotesto.jsp?categoria=Politica&pagina=130",
        "news_url": "https://www.servizitelevideo.rai.it/televideo/pub/solotesto.jsp?pagina=131",
        "content": " Aerei, il primo sciopero di Ita il 28/2 Il personale di Ita Airways sciopererà il 28 febbraio per 4 ore, dalle 10 alle 14. Lo riferiscono i sindacati dopo il mancato accordo di ieri con l'azienda. La rottura della trattativa è dovuta a posizioni divergenti sui forti aumenti di stipendio chiesti dai sindacati sia per il personale viaggiante che per  quello di terra. Nei giorni scorsa l' azienda aveva avviato la procedura per la Cigs per 400 lavoratori.  ",
        "ranked": 0,
        "placed": "Economics",
        "epoch": 1676356204.3362126,
        "language": "IT",
        "source": "Televideo"
    },
    {
        "title": "Pil Italia crescerà +0,8% nel 2023",
        "date_raw": "February 14, 2023",
        "date": "2023-02-14",
        "url": "http://www.servizitelevideo.rai.it/televideo/pub/solotesto.jsp?categoria=Politica&pagina=130",
        "news_url": "https://www.servizitelevideo.rai.it/televideo/pub/solotesto.jsp?pagina=132",
        "content": " Gentiloni: no recessione tecnica Italia \"In Italia la crescita si è contratta marginalmente nell'ultimo trimestre '22 ma si prevede che quest'anno si riprenda gradualmente e si eviti una recessione tecnica per il 2023. Così Gentiloni, commissario Ue all'Economia. Il Pil reale -proseguedovrebbe salire dello 0,8% grazie alla domanda privata ma anche ai progetti pubblici inclusi nel Pnrr, che è \"priorità,oggi,per rafforzare e incentivare gli investimenti\" Invariate stime per il Pil '24 rispetto all'autunno, crescita prevista all'1%. ",
        "ranked": 1,
        "placed": "Economics",
        "epoch": 1676356204.3509479,
        "language": "IT",
        "source": "Televideo"
    },
    {
        "title": "PARI CON LA SAMP, FRENA ANCHE L'INTER  Verona-Salernitana 1-0, gol Ngonge",
        "date_raw": "February 14, 2023",
        "date": "2023-02-14",
        "url": "http://www.servizitelevideo.rai.it/televideo/pub/solotesto.jsp?categoria=Prima&pagina=103",
        "news_url": "https://www.servizitelevideo.rai.it/televideo/pub/solotesto.jsp?pagina=201",
        "content": "     ",
        "ranked": 5,
        "placed": "First_Page",
        "epoch": 1676356204.3558404,
        "language": "IT",
        "source": "Televideo"
    },
    {
        "title": "ATTACCO ISIS IN SIRIA, ALMENO 11 MORTI  Ong:uccisi 10 civili,anche dispersi",
        "date_raw": "February 14, 2023",
        "date": "2023-02-14",
        "url": "http://www.servizitelevideo.rai.it/televideo/pub/solotesto.jsp?categoria=Dal%20Mondo&pagina=150",
        "news_url": "https://www.servizitelevideo.rai.it/televideo/pub/solotesto.jsp?pagina=156",
        "content": "",
        "ranked": 4,
        "placed": "Abroad",
        "epoch": 1676356204.368309,
        "language": "IT",
        "source": "Televideo"
    }
]
