[
    {
        "title": "New variant classed 'of concern' and named Omicron",
        "date": "2021-11-27",
        "date_raw": "2021-11-27",
        "url": "https://www.bbc.com/news/world",
        "news_url": "https://www.bbc.com/news/world-59438723",
        "content": "The World Health Organization says the variant has a large number of mutations, some are concerning.",
        "placed": "Abroad",
        "epoch": 1637974803.964271
    },
    {
        "title": "New variant classed 'of concern' and named Omicron",
        "date": "2021-11-27",
        "date_raw": "2021-11-27",
        "url": "https://www.bbc.com/news/world",
        "news_url": "https://www.bbc.com/news/world-59438723",
        "content": "The World Health Organization says the variant has a large number of mutations, some are concerning.",
        "placed": "Abroad",
        "epoch": 1637974803.9643044
    },
    {
        "title": "US joins EU in restricting southern Africa flights",
        "date": "2021-11-27",
        "date_raw": "2021-11-27",
        "url": "https://www.bbc.com/news/world",
        "news_url": "https://www.bbc.com/news/world-59427770",
        "content": "Flights from eight African nations to be blocked as new variant is classified as being \"of concern\".",
        "placed": "Abroad",
        "epoch": 1637974803.9643238
    },
    {
        "title": "Kurdish woman is first Channel victim to be named",
        "date": "2021-11-26",
        "date_raw": "2021-11-26",
        "url": "https://www.bbc.com/news/world",
        "news_url": "https://www.bbc.com/news/world-europe-59439533",
        "content": "Maryam Nuri Mohamed Amin was a 24-year-old Kurdish woman from northern Iraq.",
        "placed": "Abroad",
        "epoch": 1637974803.9643402
    },
    {
        "title": "The windswept beaches of opportunity and fear",
        "date": "2021-11-27",
        "date_raw": "2021-11-27",
        "url": "https://www.bbc.com/news/world",
        "news_url": "https://www.bbc.com/news/world-europe-59380745",
        "content": "Sunday's referendum is held in a country with one of the lowest vaccination rates in Western Europe.",
        "placed": "Abroad",
        "epoch": 1637974803.9643548
    },
    {
        "title": "Swiss vote on ending restrictions amid Covid surge",
        "date": "2021-11-26",
        "date_raw": "2021-11-26",
        "url": "https://www.bbc.com/news/world",
        "news_url": "https://www.bbc.com/news/world-europe-59428712",
        "content": "He says an alleged plan to overthrow his government comes amid threats of a Russian invasion.",
        "placed": "Abroad",
        "epoch": 1637974803.9643705
    },
    {
        "title": "Ukraine leader alleges coup plan involving Russians",
        "date": "2021-11-26",
        "date_raw": "2021-11-26",
        "url": "https://www.bbc.com/news/world",
        "news_url": "https://www.bbc.com/news/business-59428406",
        "content": "The boss of the world's largest fertiliser producer says gas prices are responsible for higher food prices.",
        "placed": "Abroad",
        "epoch": 1637974803.964386
    },
    {
        "title": "Poorest face food crisis amid fertiliser shortage",
        "date": "2021-11-27",
        "date_raw": "2021-11-27",
        "url": "https://www.bbc.com/news/world",
        "news_url": "https://www.bbc.com/news/world-59438723",
        "content": "The World Health Organization says the variant has a large number of mutations, some are concerning.",
        "placed": "Abroad",
        "epoch": 1637974803.9644012
    },
    {
        "title": "New variant classed 'of concern' and named Omicron",
        "date": "2021-11-27",
        "date_raw": "2021-11-27",
        "url": "https://www.bbc.com/news/world",
        "news_url": "https://www.bbc.com/news/world-59427770",
        "content": "Flights from eight African nations to be blocked as new variant is classified as being \"of concern\".",
        "placed": "Abroad",
        "epoch": 1637974803.9644156
    },
    {
        "title": "US joins EU in restricting southern Africa flights",
        "date": "2021-11-26",
        "date_raw": "2021-11-26",
        "url": "https://www.bbc.com/news/world",
        "news_url": "https://www.bbc.com/news/world-europe-59439533",
        "content": "Maryam Nuri Mohamed Amin was a 24-year-old Kurdish woman from northern Iraq.",
        "placed": "Abroad",
        "epoch": 1637974803.96443
    },
    {
        "title": "Kurdish woman is first Channel victim to be named",
        "date": "2021-11-27",
        "date_raw": "2021-11-27",
        "url": "https://www.bbc.com/news/world",
        "news_url": "https://www.bbc.com/news/world-europe-59380745",
        "content": "Sunday's referendum is held in a country with one of the lowest vaccination rates in Western Europe.",
        "placed": "Abroad",
        "epoch": 1637974803.9644449
    },
    {
        "title": "The windswept beaches of opportunity and fear",
        "date": "2021-11-26",
        "date_raw": "2021-11-26",
        "url": "https://www.bbc.com/news/world",
        "news_url": "https://www.bbc.com/news/world-europe-59428712",
        "content": "He says an alleged plan to overthrow his government comes amid threats of a Russian invasion.",
        "placed": "Abroad",
        "epoch": 1637974803.9644592
    },
    {
        "title": "Swiss vote on ending restrictions amid Covid surge",
        "date": "2021-11-26",
        "date_raw": "2021-11-26",
        "url": "https://www.bbc.com/news/world",
        "news_url": "https://www.bbc.com/news/business-59428406",
        "content": "The boss of the world's largest fertiliser producer says gas prices are responsible for higher food prices.",
        "placed": "Abroad",
        "epoch": 1637974803.964474
    },
    {
        "title": "Ukraine leader alleges coup plan involving Russians",
        "date": "2021-11-27",
        "date_raw": "2021-11-27",
        "url": "https://www.bbc.com/news/world",
        "news_url": "https://www.bbc.com/news/world-59427770",
        "content": "Flights from eight African nations to be blocked as new variant is classified as being \"of concern\".",
        "placed": "Abroad",
        "epoch": 1637974803.9644883
    },
    {
        "title": "Poorest face food crisis amid fertiliser shortage",
        "date": "2021-11-26",
        "date_raw": "2021-11-26",
        "url": "https://www.bbc.com/news/world",
        "news_url": "https://www.bbc.com/news/world-europe-59439533",
        "content": "Maryam Nuri Mohamed Amin was a 24-year-old Kurdish woman from northern Iraq.",
        "placed": "Abroad",
        "epoch": 1637974803.9645023
    }
]
